nexinfosys/__init__.py
nexinfosys/command_definitions.py
nexinfosys/command_descriptions.py
nexinfosys/command_field_definitions.py
nexinfosys/command_field_descriptions.py
nexinfosys/embedded_nis.py
nexinfosys/initialization.py
nexinfosys/serialization.py
nexinfosys/authentication/__init__.py
nexinfosys/bin/__init__.py
nexinfosys/bin/cli_script.py
nexinfosys/command_executors/__init__.py
nexinfosys/command_executors/execution_helpers.py
nexinfosys/command_executors/analysis/__init__.py
nexinfosys/command_executors/external_data/__init__.py
nexinfosys/command_executors/external_data/etl_external_dataset_command.py
nexinfosys/command_executors/external_data/mapping_command.py
nexinfosys/command_executors/external_data/parameters_command.py
nexinfosys/command_executors/misc/__init__.py
nexinfosys/command_executors/read_query/__init__.py
nexinfosys/command_executors/read_query/enumerate_datasets_command.py
nexinfosys/command_executors/read_query/get_dataset_query_worksheet.py
nexinfosys/command_executors/solving/__init__.py
nexinfosys/command_executors/specification/__init__.py
nexinfosys/command_executors/specification/data_input_command.py
nexinfosys/command_executors/specification/dummy_command.py
nexinfosys/command_executors/specification/hierarchy_command.py
nexinfosys/command_executors/specification/metadata_command.py
nexinfosys/command_executors/specification/pedigree_matrix_command.py
nexinfosys/command_executors/specification/references_command.py
nexinfosys/command_executors/specification/scale_conversion_command.py
nexinfosys/command_executors/specification/structure_command.py
nexinfosys/command_executors/specification/upscale_command.py
nexinfosys/command_executors/version2/__init__.py
nexinfosys/command_executors/version2/attribute_sets_command.py
nexinfosys/command_executors/version2/attribute_types_command.py
nexinfosys/command_executors/version2/dataset_data_command.py
nexinfosys/command_executors/version2/dataset_definition_command.py
nexinfosys-0.102.dist-info/LICENSE
nexinfosys-0.102.dist-info/METADATA
nexinfosys-0.102.dist-info/WHEEL
nexinfosys-0.102.dist-info/entry_points.txt
nexinfosys-0.102.dist-info/top_level.txt
nexinfosys-0.102.dist-info/RECORD
