Metadata-Version: 2.1
Name: nexinfosys
Version: 0.102
Summary: Formal and executable MuSIASEM multi-system Nexus models for Sustainable Development Analysis
Home-page: https://github.com/MAGIC-nexus/nis-backend
Author: ['Rafael Nebot', 'Marco Galluzzi']
Author-email: rnebot@itccanarias.org
License: BSD-3
Platform: UNKNOWN
License-File: LICENSE
Requires-Dist: Cython (>=0.29.7)
Requires-Dist: Flask (>=1.0.2)
Requires-Dist: Flask-Cors (==3.0.3)
Requires-Dist: Flask-Session (>=0.3.1)
Requires-Dist: NamedAtomicLock (==1.1.3)
Requires-Dist: Pint (>=0.8.1)
Requires-Dist: SQLAlchemy (>=1.3.3)
Requires-Dist: Werkzeug (>=0.15.5)
Requires-Dist: anytree (>=2.2.2)
Requires-Dist: appdirs (==1.4.3)
Requires-Dist: attrs (>=19.3.0)
Requires-Dist: blosc (>=1.8.1)
Requires-Dist: chardet (>=3.0.4)
Requires-Dist: dotted (>=0.1.8)
Requires-Dist: fire (>=0.4.0)
Requires-Dist: geojson (>=2.4.1)
Requires-Dist: google-api-python-client (==2.4.0)
Requires-Dist: google-auth-oauthlib (>=0.4.1)
Requires-Dist: google-auth (>=1.30.0)
Requires-Dist: gunicorn (==19.9.0)
Requires-Dist: jsonpickle (==1.2)
Requires-Dist: lxml (==4.6.2)
Requires-Dist: multidict (>=3.3.2)
Requires-Dist: nbformat (>=5.0.7)
Requires-Dist: networkx (>=2.2)
Requires-Dist: numpy (>=1.16.0)
Requires-Dist: openpyxl (>=3.0.7)
Requires-Dist: owlready2 (==0.23)
Requires-Dist: pandaSDMX (==0.9)
Requires-Dist: pandas (>=1.0.3)
Requires-Dist: pandas-datareader (>=0.9.0)
Requires-Dist: pycurl (>=7.43.0)
Requires-Dist: pyparsing (<=2.4.7,>=2.2.0)
Requires-Dist: redis (>=2.10.6)
Requires-Dist: regex (>=2017.11.9)
Requires-Dist: requests (>=2.21.0)
Requires-Dist: requests-cache (==0.4.13)
Requires-Dist: sdmx (>=0.2.10)
Requires-Dist: toposort (>=1.5)
Requires-Dist: xlrd (<2.0,>=1.2.0)
Requires-Dist: xlsxwriter (==1.0.4)
Requires-Dist: xmltodict (>=0.11.0)
